dodata_tutorials/cutback/1_generate_layout.ipynb
dodata_tutorials/cutback/2_generate_measurement_data.ipynb
dodata_tutorials/cutback/3_upload_measurements.ipynb
dodata_tutorials/cutback/4_download_data.ipynb
dodata_tutorials/cutback/5_delete.ipynb
dodata_tutorials/cutback/generate_layout.py
dodata_tutorials/cutback/generic.lyp
dodata_tutorials/resistance/1_generate_layout.ipynb
dodata_tutorials/resistance/2_generate_measurement_data.ipynb
dodata_tutorials/resistance/3_upload_measurements.ipynb
dodata_tutorials/resistance/4_download_data.ipynb
dodata_tutorials/resistance/5_delete.ipynb
dodata_tutorials/resistance/generate_layout.py
dodata_tutorials/resistance/test_chip.lyp
dodata_tutorials/rings/1_generate_layout.ipynb
dodata_tutorials/rings/2_generate_measurement_data.ipynb
dodata_tutorials/rings/3_upload_measurements.ipynb
dodata_tutorials/rings/4_download_data.ipynb
dodata_tutorials/rings/5_delete.ipynb
dodata_tutorials/rings/generate_layout.py
dodata_tutorials/rings/generic.lyp
dodata_tutorials/spirals/1_generate_layout.ipynb
dodata_tutorials/spirals/2_generate_measurement_data.ipynb
dodata_tutorials/spirals/3_upload_measurements.ipynb
dodata_tutorials/spirals/4_download_data.ipynb
dodata_tutorials/spirals/5_delete.ipynb
dodata_tutorials/spirals/loss_measurements.lyp
dodata_tutorials/spirals/test_chip.py
doplaydo/dodata/__init__.py
doplaydo/dodata/config.py
doplaydo/dodata/engine.py
doplaydo/dodata/py.typed
doplaydo/dodata/analysis_functions/__init__.py
doplaydo/dodata/analysis_functions/device_data/__init__.py
doplaydo/dodata/analysis_functions/device_data/fsr.py
doplaydo/dodata/analysis_functions/device_data/iv_resistance.py
doplaydo/dodata/analysis_functions/device_data/power_envelope.py
doplaydo/dodata/analysis_functions/die/__init__.py
doplaydo/dodata/analysis_functions/die/aggregate.py
doplaydo/dodata/analysis_functions/die/cutback.py
doplaydo/dodata/analysis_functions/die/iv_sheet_resistance.py
doplaydo/dodata/analysis_functions/die/loss_cutback.py
dodata-0.7.2.dist-info/LICENSE
dodata-0.7.2.dist-info/METADATA
dodata-0.7.2.dist-info/WHEEL
dodata-0.7.2.dist-info/top_level.txt
dodata-0.7.2.dist-info/RECORD
