Metadata-Version: 2.2
Name: dodata
Version: 0.7.2
Summary: Software Development Kit - SDK for DoData
Author-email: DoPlayDo <contact@doplaydo.com>
License: The MIT License (MIT)
Classifier: Programming Language :: Python :: 3.11
Classifier: Programming Language :: Python :: 3.12
Classifier: Operating System :: OS Independent
Requires-Python: >=3.11
License-File: LICENSE
Requires-Dist: dodata_core==0.5.1
Requires-Dist: klayout<0.29.12,>=0.28.15
Requires-Dist: pandas
Requires-Dist: pillow
Requires-Dist: httpx[http2]
Requires-Dist: psycopg2-binary
Requires-Dist: pydantic<3,>=2
Requires-Dist: pydantic-settings
Requires-Dist: sqlmodel>=0.0.14
Requires-Dist: tqdm
Provides-Extra: demos
Requires-Dist: gdsfactory~=9.0.3; extra == "demos"
Requires-Dist: jupyterlab; extra == "demos"
Requires-Dist: plotly<6; extra == "demos"
Provides-Extra: dev
Requires-Dist: ruff; extra == "dev"
Requires-Dist: mypy; extra == "dev"
Requires-Dist: pre-commit; extra == "dev"
Requires-Dist: pytest; extra == "dev"
Requires-Dist: towncrier; extra == "dev"
Requires-Dist: tbump; extra == "dev"
Requires-Dist: pytest_regressions; extra == "dev"
Requires-Dist: pytest-cov; extra == "dev"
Provides-Extra: docs
Requires-Dist: jupyter-book<1.1,>=0.15.1; extra == "docs"
Requires-Dist: jupytext; extra == "docs"
Requires-Dist: matplotlib; extra == "docs"
Provides-Extra: maintainer
Requires-Dist: eralchemy2; extra == "maintainer"
Requires-Dist: types-cachetools; extra == "maintainer"
Requires-Dist: types-requests; extra == "maintainer"
Requires-Dist: types-requests; extra == "maintainer"
Requires-Dist: types-setuptools; extra == "maintainer"
Requires-Dist: types-docutils; extra == "maintainer"
Requires-Dist: types-Pygments; extra == "maintainer"
Requires-Dist: pylsp-mypy; extra == "maintainer"
Requires-Dist: python-lsp-server[all]; extra == "maintainer"
Requires-Dist: python-lsp-ruff; extra == "maintainer"
